feilian/__init__.py
feilian/_dist_ver.py
feilian/_typing.py
feilian/arg.py
feilian/dataframe.py
feilian/datetime.py
feilian/excel.py
feilian/io.py
feilian/json.py
feilian/process.py
feilian/string.py
feilian/txt.py
feilian/utils.py
feilian/version.py
feilian-1.3.6.dist-info/METADATA
feilian-1.3.6.dist-info/WHEEL
feilian-1.3.6.dist-info/top_level.txt
feilian-1.3.6.dist-info/RECORD
