Metadata-Version: 2.4
Name: feilian
Version: 1.3.6
Summary: General data processing tool.
Author-email: darkpeath <darkpeath@gmail.com>
Project-URL: Homepage, https://github.com/darkpeath/feilian
Requires-Dist: chardet
Requires-Dist: pandas
Provides-Extra: extra
Requires-Dist: tqdm; extra == "extra"
Requires-Dist: ijson; extra == "extra"
